jonazarov/AtlassianCloudRest.py
jonazarov/__init__.py
jonazarov/utils.py
jonazarov-0.1.2.dist-info/LICENSE
jonazarov-0.1.2.dist-info/METADATA
jonazarov-0.1.2.dist-info/WHEEL
jonazarov-0.1.2.dist-info/top_level.txt
jonazarov-0.1.2.dist-info/RECORD
